{
  "uri": {
    "namespace": "http://data.telegraph.co.uk/resource/",
    "localName": "kfxl6S6C32l"
  },
  "name": "Hilton Luxor Resort & Spa",
  "locations": [
    {
      "id": "kJv4VNySknc",
      "type": "Continent",
      "label": "Africa",
      "lat": -8.783195,
      "long": 34.508523
    },
    {
      "id": "kJv4VN05Sb7",
      "type": "Country",
      "label": "Egypt",
      "lat": 26.820553,
      "long": 30.802498
    },
    {
      "id": "kfvWQQRNbFW",
      "type": "City",
      "label": "Luxor",
      "lat": 25.6872431,
      "long": 32.639635699999985
    },
    {
      "id": "k7RB4ZDnHrc",
      "type": "Address",
      "label": "PO Box 13, New Karnak, Luxor, Egypt.",
      "lat": 25.730228,
      "long": 32.65655800000002
    },
    {
      "id": "lBp8ZQnHtyr",
      "type": "Region",
      "label": "North Africa",
      "lat": 23.4162027,
      "long": 25.662829999999985
    }
  ],
  "types": [
    {
      "id": "khjGN7CCQDg",
      "label": "Hotel"
    },
    {
      "id": "khjG2yf0Zzj",
      "label": "Resort"
    }
  ],
  "activeOffers": [
    {
      "id": "l9LGf7ctZxW",
      "label": "Pursue your passions"
    }
  ],
  "facilities": [
    {
      "id": "kb0JyGx7S7C",
      "label": "Laundry"
    },
    {
      "id": "kb0JyGxRXSk",
      "label": "Wi-Fi"
    },
    {
      "id": "kb0JyGxW44F",
      "label": "Spa"
    },
    {
      "id": "kb0JyGyLZ4K",
      "label": "Bar"
    },
    {
      "id": "kb104pLq07J",
      "label": "Fitness centre"
    },
    {
      "id": "kb0JyGxrqXR",
      "label": "Room service"
    },
    {
      "id": "kb0JyGyBFv5",
      "label": "Restaurant"
    },
    {
      "id": "kb0JyGxZyV6",
      "label": "Steam room/hammam"
    },
    {
      "id": "kb0JyGxcP4B",
      "label": "Pool"
    },
    {
      "id": "kb0JyGxdq5p",
      "label": "Golf course"
    }
  ],
  "styles": [],
  "activePartner": {
    "label": "Booking.com",
    "id": "kKPg1rKDrKJ",
    "productId": "47730",
    "logos": [],
    "accreditations": [],
    "contactDetails": []
  },
  "contacts": [
    {
      "label": "00 2 09 5239 9999",
      "type": "Main Number",
      "alternativeLabel": null,
      "notes": null
    },
    {
      "label": "http://www.hiltonluxor.com",
      "type": "Website",
      "alternativeLabel": "http://www.hiltonluxor.com",
      "notes": null
    }
  ],
  "externalData": {
    "id": null,
    "checkIn": {
      "from": "14:00",
      "to": "00:00"
    },
    "checkOut": {
      "from": "12:00",
      "to": "13:00"
    },
    "pics": [
      {
        "url_medium": "http://aff.bstatic.com/images/hotel/max500/136/13603367.jpg",
        "url_xsmall": "http://aff.bstatic.com/images/hotel/max300/136/13603367.jpg"
      },
      {
        "url_medium": "http://aff.bstatic.com/images/hotel/max500/109/10977990.jpg",
        "url_xsmall": "http://aff.bstatic.com/images/hotel/max300/109/10977990.jpg"
      },
      {
        "url_medium": "http://aff.bstatic.com/images/hotel/max500/160/16066259.jpg",
        "url_xsmall": "http://aff.bstatic.com/images/hotel/max300/160/16066259.jpg"
      },
      {
        "url_medium": "http://aff.bstatic.com/images/hotel/max500/160/16063859.jpg",
        "url_xsmall": "http://aff.bstatic.com/images/hotel/max300/160/16063859.jpg"
      },
      {
        "url_medium": "http://aff.bstatic.com/images/hotel/max500/136/13602581.jpg",
        "url_xsmall": "http://aff.bstatic.com/images/hotel/max300/136/13602581.jpg"
      },
      {
        "url_medium": "http://aff.bstatic.com/images/hotel/max500/835/8356947.jpg",
        "url_xsmall": "http://aff.bstatic.com/images/hotel/max300/835/8356947.jpg"
      },
      {
        "url_medium": "http://aff.bstatic.com/images/hotel/max500/136/13602927.jpg",
        "url_xsmall": "http://aff.bstatic.com/images/hotel/max300/136/13602927.jpg"
      },
      {
        "url_medium": "http://aff.bstatic.com/images/hotel/max500/136/13602917.jpg",
        "url_xsmall": "http://aff.bstatic.com/images/hotel/max300/136/13602917.jpg"
      },
      {
        "url_medium": "http://aff.bstatic.com/images/hotel/max500/136/13603017.jpg",
        "url_xsmall": "http://aff.bstatic.com/images/hotel/max300/136/13603017.jpg"
      },
      {
        "url_medium": "http://aff.bstatic.com/images/hotel/max500/136/13603134.jpg",
        "url_xsmall": "http://aff.bstatic.com/images/hotel/max300/136/13603134.jpg"
      },
      {
        "url_medium": "http://aff.bstatic.com/images/hotel/max500/136/13603157.jpg",
        "url_xsmall": "http://aff.bstatic.com/images/hotel/max300/136/13603157.jpg"
      },
      {
        "url_medium": "http://aff.bstatic.com/images/hotel/max500/835/8356704.jpg",
        "url_xsmall": "http://aff.bstatic.com/images/hotel/max300/835/8356704.jpg"
      },
      {
        "url_medium": "http://aff.bstatic.com/images/hotel/max500/835/8357001.jpg",
        "url_xsmall": "http://aff.bstatic.com/images/hotel/max300/835/8357001.jpg"
      },
      {
        "url_medium": "http://aff.bstatic.com/images/hotel/max500/835/8356917.jpg",
        "url_xsmall": "http://aff.bstatic.com/images/hotel/max300/835/8356917.jpg"
      },
      {
        "url_medium": "http://aff.bstatic.com/images/hotel/max500/835/8357041.jpg",
        "url_xsmall": "http://aff.bstatic.com/images/hotel/max300/835/8357041.jpg"
      },
      {
        "url_medium": "http://aff.bstatic.com/images/hotel/max500/835/8357064.jpg",
        "url_xsmall": "http://aff.bstatic.com/images/hotel/max300/835/8357064.jpg"
      },
      {
        "url_medium": "http://aff.bstatic.com/images/hotel/max500/161/16122569.jpg",
        "url_xsmall": "http://aff.bstatic.com/images/hotel/max300/161/16122569.jpg"
      },
      {
        "url_medium": "http://aff.bstatic.com/images/hotel/max500/136/13602920.jpg",
        "url_xsmall": "http://aff.bstatic.com/images/hotel/max300/136/13602920.jpg"
      },
      {
        "url_medium": "http://aff.bstatic.com/images/hotel/max500/835/8356792.jpg",
        "url_xsmall": "http://aff.bstatic.com/images/hotel/max300/835/8356792.jpg"
      },
      {
        "url_medium": "http://aff.bstatic.com/images/hotel/max500/136/13603329.jpg",
        "url_xsmall": "http://aff.bstatic.com/images/hotel/max300/136/13603329.jpg"
      },
      {
        "url_medium": "http://aff.bstatic.com/images/hotel/max500/136/13602953.jpg",
        "url_xsmall": "http://aff.bstatic.com/images/hotel/max300/136/13602953.jpg"
      },
      {
        "url_medium": "http://aff.bstatic.com/images/hotel/max500/136/13603459.jpg",
        "url_xsmall": "http://aff.bstatic.com/images/hotel/max300/136/13603459.jpg"
      },
      {
        "url_medium": "http://aff.bstatic.com/images/hotel/max500/835/8357098.jpg",
        "url_xsmall": "http://aff.bstatic.com/images/hotel/max300/835/8357098.jpg"
      },
      {
        "url_medium": "http://aff.bstatic.com/images/hotel/max500/136/13603173.jpg",
        "url_xsmall": "http://aff.bstatic.com/images/hotel/max300/136/13603173.jpg"
      },
      {
        "url_medium": "http://aff.bstatic.com/images/hotel/max500/835/8356248.jpg",
        "url_xsmall": "http://aff.bstatic.com/images/hotel/max300/835/8356248.jpg"
      },
      {
        "url_medium": "http://aff.bstatic.com/images/hotel/max500/835/8356848.jpg",
        "url_xsmall": "http://aff.bstatic.com/images/hotel/max300/835/8356848.jpg"
      },
      {
        "url_medium": "http://aff.bstatic.com/images/hotel/max500/136/13602593.jpg",
        "url_xsmall": "http://aff.bstatic.com/images/hotel/max300/136/13602593.jpg"
      },
      {
        "url_medium": "http://aff.bstatic.com/images/hotel/max500/136/13602769.jpg",
        "url_xsmall": "http://aff.bstatic.com/images/hotel/max300/136/13602769.jpg"
      },
      {
        "url_medium": "http://aff.bstatic.com/images/hotel/max500/136/13603383.jpg",
        "url_xsmall": "http://aff.bstatic.com/images/hotel/max300/136/13603383.jpg"
      },
      {
        "url_medium": "http://aff.bstatic.com/images/hotel/max500/136/13603436.jpg",
        "url_xsmall": "http://aff.bstatic.com/images/hotel/max300/136/13603436.jpg"
      },
      {
        "url_medium": "http://aff.bstatic.com/images/hotel/max500/835/8356448.jpg",
        "url_xsmall": "http://aff.bstatic.com/images/hotel/max300/835/8356448.jpg"
      },
      {
        "url_medium": "http://aff.bstatic.com/images/hotel/max500/136/13603429.jpg",
        "url_xsmall": "http://aff.bstatic.com/images/hotel/max300/136/13603429.jpg"
      },
      {
        "url_medium": "http://aff.bstatic.com/images/hotel/max500/874/8748445.jpg",
        "url_xsmall": "http://aff.bstatic.com/images/hotel/max300/874/8748445.jpg"
      },
      {
        "url_medium": "http://aff.bstatic.com/images/hotel/max500/835/8355580.jpg",
        "url_xsmall": "http://aff.bstatic.com/images/hotel/max300/835/8355580.jpg"
      },
      {
        "url_medium": "http://aff.bstatic.com/images/hotel/max500/136/13603028.jpg",
        "url_xsmall": "http://aff.bstatic.com/images/hotel/max300/136/13603028.jpg"
      },
      {
        "url_medium": "http://aff.bstatic.com/images/hotel/max500/136/13602895.jpg",
        "url_xsmall": "http://aff.bstatic.com/images/hotel/max300/136/13602895.jpg"
      },
      {
        "url_medium": "http://aff.bstatic.com/images/hotel/max500/136/13603302.jpg",
        "url_xsmall": "http://aff.bstatic.com/images/hotel/max300/136/13603302.jpg"
      },
      {
        "url_medium": "http://aff.bstatic.com/images/hotel/max500/835/8355680.jpg",
        "url_xsmall": "http://aff.bstatic.com/images/hotel/max300/835/8355680.jpg"
      },
      {
        "url_medium": "http://aff.bstatic.com/images/hotel/max500/159/15929815.jpg",
        "url_xsmall": "http://aff.bstatic.com/images/hotel/max300/159/15929815.jpg"
      },
      {
        "url_medium": "http://aff.bstatic.com/images/hotel/max500/835/8355663.jpg",
        "url_xsmall": "http://aff.bstatic.com/images/hotel/max300/835/8355663.jpg"
      },
      {
        "url_medium": "http://aff.bstatic.com/images/hotel/max500/835/8356193.jpg",
        "url_xsmall": "http://aff.bstatic.com/images/hotel/max300/835/8356193.jpg"
      },
      {
        "url_medium": "http://aff.bstatic.com/images/hotel/max500/136/13603435.jpg",
        "url_xsmall": "http://aff.bstatic.com/images/hotel/max300/136/13603435.jpg"
      },
      {
        "url_medium": "http://aff.bstatic.com/images/hotel/max500/136/13603432.jpg",
        "url_xsmall": "http://aff.bstatic.com/images/hotel/max300/136/13603432.jpg"
      },
      {
        "url_medium": "http://aff.bstatic.com/images/hotel/max500/136/13603108.jpg",
        "url_xsmall": "http://aff.bstatic.com/images/hotel/max300/136/13603108.jpg"
      },
      {
        "url_medium": "http://aff.bstatic.com/images/hotel/max500/136/13602702.jpg",
        "url_xsmall": "http://aff.bstatic.com/images/hotel/max300/136/13602702.jpg"
      },
      {
        "url_medium": "http://aff.bstatic.com/images/hotel/max500/136/13603265.jpg",
        "url_xsmall": "http://aff.bstatic.com/images/hotel/max300/136/13603265.jpg"
      },
      {
        "url_medium": "http://aff.bstatic.com/images/hotel/max500/136/13603412.jpg",
        "url_xsmall": "http://aff.bstatic.com/images/hotel/max300/136/13603412.jpg"
      },
      {
        "url_medium": "http://aff.bstatic.com/images/hotel/max500/835/8355706.jpg",
        "url_xsmall": "http://aff.bstatic.com/images/hotel/max300/835/8355706.jpg"
      },
      {
        "url_medium": "http://aff.bstatic.com/images/hotel/max500/136/13603362.jpg",
        "url_xsmall": "http://aff.bstatic.com/images/hotel/max300/136/13603362.jpg"
      },
      {
        "url_medium": "http://aff.bstatic.com/images/hotel/max500/136/13602892.jpg",
        "url_xsmall": "http://aff.bstatic.com/images/hotel/max300/136/13602892.jpg"
      },
      {
        "url_medium": "http://aff.bstatic.com/images/hotel/max500/136/13602975.jpg",
        "url_xsmall": "http://aff.bstatic.com/images/hotel/max300/136/13602975.jpg"
      },
      {
        "url_medium": "http://aff.bstatic.com/images/hotel/max500/835/8356429.jpg",
        "url_xsmall": "http://aff.bstatic.com/images/hotel/max300/835/8356429.jpg"
      },
      {
        "url_medium": "http://aff.bstatic.com/images/hotel/max500/835/8356466.jpg",
        "url_xsmall": "http://aff.bstatic.com/images/hotel/max300/835/8356466.jpg"
      },
      {
        "url_medium": "http://aff.bstatic.com/images/hotel/max500/835/8356966.jpg",
        "url_xsmall": "http://aff.bstatic.com/images/hotel/max300/835/8356966.jpg"
      },
      {
        "url_medium": "http://aff.bstatic.com/images/hotel/max500/136/13603132.jpg",
        "url_xsmall": "http://aff.bstatic.com/images/hotel/max300/136/13603132.jpg"
      },
      {
        "url_medium": "http://aff.bstatic.com/images/hotel/max500/136/13603142.jpg",
        "url_xsmall": "http://aff.bstatic.com/images/hotel/max300/136/13603142.jpg"
      },
      {
        "url_medium": "http://aff.bstatic.com/images/hotel/max500/136/13603152.jpg",
        "url_xsmall": "http://aff.bstatic.com/images/hotel/max300/136/13603152.jpg"
      },
      {
        "url_medium": "http://aff.bstatic.com/images/hotel/max500/136/13603448.jpg",
        "url_xsmall": "http://aff.bstatic.com/images/hotel/max300/136/13603448.jpg"
      },
      {
        "url_medium": "http://aff.bstatic.com/images/hotel/max500/150/15067628.jpg",
        "url_xsmall": "http://aff.bstatic.com/images/hotel/max300/150/15067628.jpg"
      },
      {
        "url_medium": "http://aff.bstatic.com/images/hotel/max500/136/13603402.jpg",
        "url_xsmall": "http://aff.bstatic.com/images/hotel/max300/136/13603402.jpg"
      },
      {
        "url_medium": "http://aff.bstatic.com/images/hotel/max500/835/8356889.jpg",
        "url_xsmall": "http://aff.bstatic.com/images/hotel/max300/835/8356889.jpg"
      },
      {
        "url_medium": "http://aff.bstatic.com/images/hotel/max500/835/8356553.jpg",
        "url_xsmall": "http://aff.bstatic.com/images/hotel/max300/835/8356553.jpg"
      },
      {
        "url_medium": "http://aff.bstatic.com/images/hotel/max500/835/8357076.jpg",
        "url_xsmall": "http://aff.bstatic.com/images/hotel/max300/835/8357076.jpg"
      },
      {
        "url_medium": "http://aff.bstatic.com/images/hotel/max500/835/8357083.jpg",
        "url_xsmall": "http://aff.bstatic.com/images/hotel/max300/835/8357083.jpg"
      },
      {
        "url_medium": "http://aff.bstatic.com/images/hotel/max500/835/8356873.jpg",
        "url_xsmall": "http://aff.bstatic.com/images/hotel/max300/835/8356873.jpg"
      }
    ],
    "hotelUrl": "https://www.booking.com/hotel/eg/hilton-luxor-resort-spa.html",
    "reservationUrl": "https://www.booking.com/hotel/eg/hilton-luxor-resort-spa.html",
    "rooms": [
      {
        "images": [
          {
            "url_medium": "http://aff.bstatic.com/images/hotel/max500/161/16122569.jpg",
            "url_xsmall": "http://aff.bstatic.com/images/hotel/max300/161/16122569.jpg"
          },
          {
            "url_medium": "http://aff.bstatic.com/images/hotel/max500/835/8356873.jpg",
            "url_xsmall": "http://aff.bstatic.com/images/hotel/max300/835/8356873.jpg"
          }
        ],
        "id": "4773012",
        "name": null,
        "price_from": "0",
        "description": null,
        "sleeps_adults": "2",
        "size": "28.00"
      },
      {
        "images": [],
        "id": "4773003",
        "name": null,
        "price_from": "0",
        "description": null,
        "sleeps_adults": "2",
        "size": "28.00"
      },
      {
        "images": [
          {
            "url_medium": "http://aff.bstatic.com/images/hotel/max500/835/8356448.jpg",
            "url_xsmall": "http://aff.bstatic.com/images/hotel/max300/835/8356448.jpg"
          },
          {
            "url_medium": "http://aff.bstatic.com/images/hotel/max500/136/13603017.jpg",
            "url_xsmall": "http://aff.bstatic.com/images/hotel/max300/136/13603017.jpg"
          }
        ],
        "id": "4773006",
        "name": null,
        "price_from": "0",
        "description": null,
        "sleeps_adults": "2",
        "size": "32.00"
      },
      {
        "images": [
          {
            "url_medium": "http://aff.bstatic.com/images/hotel/max500/835/8356248.jpg",
            "url_xsmall": "http://aff.bstatic.com/images/hotel/max300/835/8356248.jpg"
          },
          {
            "url_medium": "http://aff.bstatic.com/images/hotel/max500/835/8356193.jpg",
            "url_xsmall": "http://aff.bstatic.com/images/hotel/max300/835/8356193.jpg"
          },
          {
            "url_medium": "http://aff.bstatic.com/images/hotel/max500/835/8356553.jpg",
            "url_xsmall": "http://aff.bstatic.com/images/hotel/max300/835/8356553.jpg"
          }
        ],
        "id": "4773010",
        "name": null,
        "price_from": "0",
        "description": null,
        "sleeps_adults": "3",
        "size": "56.00"
      },
      {
        "images": [
          {
            "url_medium": "http://aff.bstatic.com/images/hotel/max500/835/8356405.jpg",
            "url_xsmall": "http://aff.bstatic.com/images/hotel/max300/835/8356405.jpg"
          }
        ],
        "id": "4773013",
        "name": null,
        "price_from": "0",
        "description": null,
        "sleeps_adults": "3",
        "size": "36.00"
      },
      {
        "images": [],
        "id": "4773001",
        "name": null,
        "price_from": "88",
        "description": null,
        "sleeps_adults": "2",
        "size": "28.00"
      },
      {
        "images": [
          {
            "url_medium": "http://aff.bstatic.com/images/hotel/max500/835/8356466.jpg",
            "url_xsmall": "http://aff.bstatic.com/images/hotel/max300/835/8356466.jpg"
          }
        ],
        "id": "4773004",
        "name": null,
        "price_from": "0",
        "description": null,
        "sleeps_adults": "2",
        "size": "32.00"
      },
      {
        "images": [
          {
            "url_medium": "http://aff.bstatic.com/images/hotel/max500/835/8356429.jpg",
            "url_xsmall": "http://aff.bstatic.com/images/hotel/max300/835/8356429.jpg"
          }
        ],
        "id": "4773011",
        "name": null,
        "price_from": "0",
        "description": null,
        "sleeps_adults": "2",
        "size": "28.00"
      },
      {
        "images": [
          {
            "url_medium": "http://aff.bstatic.com/images/hotel/max500/835/8357001.jpg",
            "url_xsmall": "http://aff.bstatic.com/images/hotel/max300/835/8357001.jpg"
          },
          {
            "url_medium": "http://aff.bstatic.com/images/hotel/max500/874/8748445.jpg",
            "url_xsmall": "http://aff.bstatic.com/images/hotel/max300/874/8748445.jpg"
          },
          {
            "url_medium": "http://aff.bstatic.com/images/hotel/max500/835/8356966.jpg",
            "url_xsmall": "http://aff.bstatic.com/images/hotel/max300/835/8356966.jpg"
          },
          {
            "url_medium": "http://aff.bstatic.com/images/hotel/max500/835/8357083.jpg",
            "url_xsmall": "http://aff.bstatic.com/images/hotel/max300/835/8357083.jpg"
          }
        ],
        "id": "4773014",
        "name": null,
        "price_from": "0",
        "description": null,
        "sleeps_adults": "3",
        "size": "65.00"
      }
    ],
    "roomCount": "236",
    "priceFrom": "63.69",
    "city_id": "-290821"
  },
  "priceFrom": "63.69",
  "averageRating": 7.4,
  "geoLocalisationHint": "Luxor, Egypt"
}