{
  "uri": {
    "namespace": "http://data.telegraph.co.uk/resource/",
    "localName": "k3kWmhGH9Sm"
  },
  "name": "Waldorf Astoria New York",
  "locations": [
    {
      "id": "kJv4VPBQggy",
      "type": "City",
      "label": "New York",
      "lat": 40.7127837,
      "long": -74.0059413
    },
    {
      "id": "kJv4VN7rmZ6",
      "type": "Continent",
      "label": "North America",
      "lat": 54.5259614,
      "long": -105.2551187
    },
    {
      "id": "kJv4VN9Y0pL",
      "type": "Country",
      "label": "United States",
      "lat": 37.09024,
      "long": -95.712891
    },
    {
      "id": "kJv4VN9qk9F",
      "type": "Region",
      "label": "New York State",
      "lat": 43.2994285,
      "long": -74.21793260000001
    },
    {
      "id": "k7RBnQhJ2k7",
      "type": "Address",
      "label": "301 Park Avenue, New York, 10022, United States.",
      "lat": 40.75674333291594,
      "long": -73.97383600473398
    }
  ],
  "types": [
    {
      "id": "khjGN7CCQDg",
      "label": "Hotel"
    }
  ],
  "activeOffers": [],
  "facilities": [
    {
      "id": "kb0JyGx7S7C",
      "label": "Laundry"
    },
    {
      "id": "kb0JyGxRXSk",
      "label": "Wi-Fi"
    },
    {
      "id": "kb0JyGxW44F",
      "label": "Spa"
    },
    {
      "id": "kb0JyGxbP5x",
      "label": "Parking"
    },
    {
      "id": "kb0JyGyLZ4K",
      "label": "Bar"
    },
    {
      "id": "kb104pLq07J",
      "label": "Fitness centre"
    },
    {
      "id": "kb0JyGxrqXR",
      "label": "Room service"
    },
    {
      "id": "kb0JyGyBFv5",
      "label": "Restaurant"
    }
  ],
  "styles": [],
  "activePartner": {
    "label": "Booking.com",
    "id": "kKPg1rKDrKJ",
    "productId": "28634",
    "logos": [],
    "accreditations": [],
    "contactDetails": []
  },
  "contacts": [
    {
      "label": "001 212 872 1275",
      "type": "Main Number",
      "alternativeLabel": null,
      "notes": null
    },
    {
      "label": "waldorfnewyork.com",
      "type": "Website",
      "alternativeLabel": "http://www.waldorfnewyork.com/",
      "notes": null
    }
  ],
  "externalData": {
    "id": null,
    "checkIn": null,
    "checkOut": null,
    "pics": null,
    "hotelUrl": null,
    "reservationUrl": null,
    "rooms": [],
    "roomCount": null,
    "priceFrom": "153.79",
    "city_id": null
  },
  "priceFrom": "153.79",
  "averageRating": 7.5,
  "geoLocalisationHint": "New York, United States"
}